README.md
setup.py
elastipy/__init__.py
elastipy/_json.py
elastipy/_version.py
elastipy/connections.py
elastipy/exporter.py
elastipy/generated_search_param.py
elastipy/geo_conv.py
elastipy/response_dump.py
elastipy/search.py
elastipy/search_dump.py
elastipy/search_param.py
elastipy.egg-info/PKG-INFO
elastipy.egg-info/SOURCES.txt
elastipy.egg-info/dependency_links.txt
elastipy.egg-info/not-zip-safe
elastipy.egg-info/requires.txt
elastipy.egg-info/top_level.txt
elastipy/aggregation/__init__.py
elastipy/aggregation/aggregation.py
elastipy/aggregation/aggregation_dump.py
elastipy/aggregation/converter.py
elastipy/aggregation/generated_interface.py
elastipy/aggregation/helper.py
elastipy/aggregation/interface.py
elastipy/aggregation/special.py
elastipy/aggregation/visitor.py
elastipy/dump/__init__.py
elastipy/dump/console.py
elastipy/dump/heatmap.py
elastipy/dump/helper.py
elastipy/dump/table.py
elastipy/dump/textplotter.py
elastipy/plot/__init__.py
elastipy/plot/aggregation_plot_pd.py
elastipy/plot/backend.py
elastipy/plot/heatmap_.py
elastipy/query/__init__.py
elastipy/query/bool.py
elastipy/query/empty.py
elastipy/query/generated_classes.py
elastipy/query/generated_interface.py
elastipy/query/interface.py
elastipy/query/query.py
elastipy/query/special.py